addok_fr/__init__.py
addok_fr/utils.py
addok_fr/resources/synonyms.txt
addok_fr-1.0.1.dist-info/DESCRIPTION.rst
addok_fr-1.0.1.dist-info/METADATA
addok_fr-1.0.1.dist-info/RECORD
addok_fr-1.0.1.dist-info/WHEEL
addok_fr-1.0.1.dist-info/entry_points.txt
addok_fr-1.0.1.dist-info/metadata.json
addok_fr-1.0.1.dist-info/top_level.txt
